README.md
setup.py
deebotozmo/VacBot.py
deebotozmo/__init__.py
deebotozmo/commands.py
deebotozmo/constants.py
deebotozmo/ecovacs_api.py
deebotozmo/ecovacs_json.py
deebotozmo/events.py
deebotozmo/map.py
deebotozmo/models.py
deebotozmo/util.py
deebotozmo_beta.egg-info/PKG-INFO
deebotozmo_beta.egg-info/SOURCES.txt
deebotozmo_beta.egg-info/dependency_links.txt
deebotozmo_beta.egg-info/requires.txt
deebotozmo_beta.egg-info/top_level.txt