Metadata-Version: 1.1
Name: deebotozmo-beta
Version: 0.0.4
Summary: a library for controlling certain robot vacuums
Home-page: UNKNOWN
Author: Andrea Liosi
Author-email: andrea.liosi@gmail.com
License: GPL-3.0
Keywords: home automation vacuum robot
Platform: UNKNOWN
Classifier: Development Status :: 4 - Beta
Classifier: Intended Audience :: Developers
Classifier: Topic :: Software Development :: Libraries
Classifier: Topic :: Home Automation
Classifier: License :: OSI Approved :: GNU General Public License v3 (GPLv3)
Classifier: Programming Language :: Python :: 3.8
